src/hypermri/__init__.py
src/hypermri/anatomical.py
src/hypermri/brukerexp.py
src/hypermri/spectroscopy.py
src/hypermri/utils.py
tests/__init__.py
hypermri-0.0.3.dist-info/LICENSE.txt
hypermri-0.0.3.dist-info/METADATA
hypermri-0.0.3.dist-info/WHEEL
hypermri-0.0.3.dist-info/top_level.txt
hypermri-0.0.3.dist-info/RECORD
