Metadata-Version: 2.1
Name: hypermri
Version: 0.0.3
Summary: Schilling-AG python module to work with Bruker MRI data
Author-email: Andre Wendlinger <andre.wendlinger@tum.de>, Wolfgang Gottwald <wolfgang.gottwald@tum.de>
License: GNU GENERAL PUBLIC LICENSE
Classifier: Programming Language :: Python :: 3
Classifier: Programming Language :: Python :: 3.7
Classifier: License :: OSI Approved :: GNU General Public License v3 or later (GPLv3+)
Classifier: Intended Audience :: Science/Research
Requires-Python: >=3.7
License-File: LICENSE.txt
Requires-Dist: numpy (>=1.19.5)
Requires-Dist: matplotlib (>=3.2.1)
Requires-Dist: brukerapi (>=0.1.6)
Provides-Extra: dev
Requires-Dist: black (>=22.12.0) ; extra == 'dev'
Requires-Dist: pytest (>=3.7) ; extra == 'dev'
